<?xml version="1.0" encoding="utf-8"?><toc><breadcrumbs><li><a href="0308fc10-4849-afd3-9e82-d10547e86599.htm">Docs</a></li><li><a href="0308fc10-4849-afd3-9e82-d10547e86599.htm">Financial.<wbr />Tracker</a></li><li><a href="492b80eb-1220-b9ea-41fa-83c246888534.htm">Auth<wbr />Form</a></li></breadcrumbs><tocItems><li><a id="c80b6f3f-2de2-988c-169f-69998480f94f" href="c80b6f3f-2de2-988c-169f-69998480f94f.htm">конструктор</a></li><li><a id="d88b412c-c874-545f-eebc-20b07e760ecf" class="has-submenu" href="d88b412c-c874-545f-eebc-20b07e760ecf.htm"><span data-tocFile="../toc/IDBAA.xml" class="icon toggle" onclick="ToggleExpandCollapse(this); return false;"><i class="fa fa-angle-right"> </i></span>методы</a><ul class="toc-menu is-hidden"> </ul></li><li><a id="3a0d4c8e-9a24-ce9b-fab3-29bdff484e03" class="has-submenu" href="3a0d4c8e-9a24-ce9b-fab3-29bdff484e03.htm"><span data-tocFile="../toc/IDCAA.xml" class="icon toggle" onclick="ToggleExpandCollapse(this); return false;"><i class="fa fa-angle-right"> </i></span>поля</a><ul class="toc-menu is-hidden"> </ul></li></tocItems></toc>